CHANGES.rst
MANIFEST.in
README.rst
setup.cfg
setup.py
betahaus/__init__.py
betahaus.pyracont.egg-info/PKG-INFO
betahaus.pyracont.egg-info/SOURCES.txt
betahaus.pyracont.egg-info/dependency_links.txt
betahaus.pyracont.egg-info/entry_points.txt
betahaus.pyracont.egg-info/not-zip-safe
betahaus.pyracont.egg-info/paster_plugins.txt
betahaus.pyracont.egg-info/requires.txt
betahaus.pyracont.egg-info/top_level.txt
betahaus/pyracont/__init__.py
betahaus/pyracont/decorators.py
betahaus/pyracont/events.py
betahaus/pyracont/exceptions.py
betahaus/pyracont/factories.py
betahaus/pyracont/interfaces.py
betahaus/pyracont/fields/__init__.py
betahaus/pyracont/fields/base.py
betahaus/pyracont/fields/lang.py
betahaus/pyracont/fields/password.py
betahaus/pyracont/fields/versioning.py
betahaus/pyracont/fields/tests/__init__.py
betahaus/pyracont/fields/tests/test_base.py
betahaus/pyracont/fields/tests/test_lang_field.py
betahaus/pyracont/fields/tests/test_password_field.py
betahaus/pyracont/fields/tests/test_versioning_field.py
betahaus/pyracont/tests/__init__.py
betahaus/pyracont/tests/test_base_folder.py
betahaus/pyracont/tests/test_check_unique_name.py
betahaus/pyracont/tests/test_decorators.py
betahaus/pyracont/tests/test_events.py
betahaus/pyracont/tests/test_factories.py
betahaus/pyracont/tests/fixtures/__init__.py
betahaus/pyracont/tests/fixtures/contents.py
betahaus/pyracont/tests/fixtures/override_content.py
betahaus/pyracont/tests/fixtures/override_schema.py
betahaus/pyracont/tests/fixtures/schemas.py