Metadata-Version: 1.0
Name: betahaus.pyracont
Version: 0.3b0
Summary: betahaus.pyracont
Home-page: https://github.com/robinharms/betahaus.pyracont
Author: Robin Harms Oredsson and contributors
Author-email: robin@betahaus.net
License: UNKNOWN
Keywords: web pyramid pylons
Platform: UNKNOWN
Classifier: Programming Language :: Python
Classifier: Framework :: Pyramid
Classifier: Topic :: Internet :: WWW/HTTP
Classifier: Topic :: Internet :: WWW/HTTP :: WSGI :: Application
Classifier: Intended Audience :: Developers
Classifier: License :: OSI Approved :: GNU General Public License v3 (GPLv3)
Classifier: Development Status :: 4 - Beta
